gracc_reporting/IndexPattern.py
gracc_reporting/NiceNum.py
gracc_reporting/ReportUtils.py
gracc_reporting/TextUtils.py
gracc_reporting/TimeUtils.py
gracc_reporting/__init__.py
gracc_reporting-3.4.0.dist-info/LICENSE
gracc_reporting-3.4.0.dist-info/METADATA
gracc_reporting-3.4.0.dist-info/WHEEL
gracc_reporting-3.4.0.dist-info/top_level.txt
gracc_reporting-3.4.0.dist-info/RECORD
