Metadata-Version: 2.1
Name: gracc-reporting
Version: 3.4.0
Summary: GRACC Email Reports
Home-page: https://github.com/opensciencegrid/gracc-reporting
Author: Shreyas Bhat
Author-email: sbhat@fnal.gov
License-File: LICENSE
Requires-Dist: elasticsearch
Requires-Dist: elasticsearch-dsl
Requires-Dist: python-dateutil
Requires-Dist: toml
Requires-Dist: tabulate
Requires-Dist: pandas
